ap2test/__init__.py
ap2test/cli.py
ap2test/harness.py
ap2test/mandates.py
ap2test-0.1.2.dist-info/licenses/LICENSE
ap2test-0.1.2.dist-info/METADATA
ap2test-0.1.2.dist-info/WHEEL
ap2test-0.1.2.dist-info/entry_points.txt
ap2test-0.1.2.dist-info/top_level.txt
ap2test-0.1.2.dist-info/RECORD
