Metadata-Version: 2.4
Name: ap2test
Version: 0.1.2
Summary: CLI tool for testing Agent Payments Protocol (AP2) implementations
Author: Evan Kirtz
Author-email: Evan Kirtz <kirtzevan@gmail.com>
Maintainer-email: Evan Kirtz <kirtzevan@gmail.com>
License: MIT
Project-URL: Homepage, https://github.com/edoggy777/ap2test
Project-URL: AP2 Documentation, https://ap2-protocol.org/
Keywords: ap2,agent-payments,payment-protocol,ai-agents,testing,cli
Classifier: Development Status :: 3 - Alpha
Classifier: Intended Audience :: Developers
Classifier: Topic :: Software Development :: Testing
Classifier: Topic :: Software Development :: Libraries :: Python Modules
Classifier: Environment :: Console
Classifier: License :: OSI Approved :: MIT License
Classifier: Operating System :: OS Independent
Classifier: Programming Language :: Python :: 3
Classifier: Programming Language :: Python :: 3.7
Classifier: Programming Language :: Python :: 3.8
Classifier: Programming Language :: Python :: 3.9
Classifier: Programming Language :: Python :: 3.10
Classifier: Programming Language :: Python :: 3.11
Classifier: Programming Language :: Python :: 3.12
Requires-Python: >=3.7
License-File: LICENSE
Requires-Dist: click>=8.0.0
Provides-Extra: dev
Requires-Dist: build>=0.10.0; extra == "dev"
Requires-Dist: twine>=4.0.0; extra == "dev"
Requires-Dist: pytest>=7.0.0; extra == "dev"
Dynamic: author
Dynamic: license-file
Dynamic: requires-python
